AUTHORS
LICENSE
MANIFEST.in
README.md
setup.py
django_choices_enum/__init__.py
django_choices_enum/_version.py
django_choices_enum/base.py
django_choices_enum.egg-info/PKG-INFO
django_choices_enum.egg-info/SOURCES.txt
django_choices_enum.egg-info/dependency_links.txt
django_choices_enum.egg-info/requires.txt
django_choices_enum.egg-info/top_level.txt
tests/__init__.py
tests/test_basic.py