Metadata-Version: 1.1
Name: django-choices-enum
Version: 0.2
Summary: make enum34 package play well with django choices
Home-page: http://github.com/tcwang817/django-choices-enum
Author: Tommy Wang
Author-email: twang@joinem.com
License: MIT
Download-URL: https://github.com/tcwang817/django-choices-enum/tarball/0.2
Keywords: django choices enum
Platform: any
Classifier: Development Status :: 4 - Beta
Classifier: Intended Audience :: Developers
Classifier: Topic :: Software Development :: Libraries :: Python Modules
Classifier: Environment :: Web Environment
Classifier: Topic :: Internet
Classifier: License :: OSI Approved :: MIT License
Classifier: Operating System :: OS Independent
Classifier: Programming Language :: Python
Classifier: Programming Language :: Python :: 2.6
Classifier: Programming Language :: Python :: 2.7
Classifier: Framework :: Django
